setup.cfg
setup.py
steamer/__init__.py
steamer/steamer.py
steamer.egg-info/PKG-INFO
steamer.egg-info/SOURCES.txt
steamer.egg-info/dependency_links.txt
steamer.egg-info/entry_points.txt
steamer.egg-info/top_level.txt
test/test_steamer.py