Metadata-Version: 1.1
Name: steamer
Version: 0.1.1
Summary: Do things when files change
Home-page: https://github.com/martylookalike/steamer
Author: martylookalike
Author-email: martylookalike@users.noreply.github.com
License: UNKNOWN
Download-URL: https://github.com/martylookalike/steamer/tarball/0.1
Keywords: testing,task,tasks
Platform: UNKNOWN
